conlang/__init__.py
conlang/language.py
conlang/language_config.py
conlang/loader.py
conlang/phonemes.py
conlang/presets.py
conlang/rules.py
conlang/sound_change.py
conlang/swadesh.py
conlang/utils.py
conlang/vocabulary.py
conlang/word.py
conlang/tests/__init__.py
conlang/tests/conftest.py
conlang/tests/test_sound_change.py
conlang-0.4.0.dist-info/licenses/LICENSE
conlang-0.4.0.dist-info/METADATA
conlang-0.4.0.dist-info/WHEEL
conlang-0.4.0.dist-info/top_level.txt
conlang-0.4.0.dist-info/RECORD
