Metadata-Version: 2.4
Name: conlang
Version: 0.4.0
Summary: A package for creating and manipulating constructed languages
Home-page: https://github.com/hlan0/conlang
Author: Jonas Gregorio
Classifier: Programming Language :: Python :: 3
Classifier: License :: OSI Approved :: GNU General Public License v3 (GPLv3)
Classifier: Operating System :: OS Independent
Requires-Python: >=3.7
License-File: LICENSE
Requires-Dist: numpy
Dynamic: license-file
Dynamic: requires-dist
